NetVizCorpy/__init__.py
NetVizCorpy/deriveNetwork.py
NetVizCorpy/identifyQIDs.py
NetVizCorpy/postProcess.py
NetVizCorpy/query.py
NetVizCorpy/version.py
NetVizCorpy/visualiseNetwork.py
netvizcorpy-0.1.7.dist-info/licenses/LICENSE
netvizcorpy-0.1.7.dist-info/METADATA
netvizcorpy-0.1.7.dist-info/WHEEL
netvizcorpy-0.1.7.dist-info/top_level.txt
netvizcorpy-0.1.7.dist-info/RECORD
