Metadata-Version: 2.4
Name: NetVizCorpy
Version: 0.1.7
Summary: Visualise corporate relationships using WikiData in multi-level B2B networks
Home-page: https://github.com/zb15/NetVizCorpy
Author: Zsofia Baruwa
Author-email: zb78@kent.ac.uk
Classifier: Programming Language :: Python :: 3
Classifier: License :: OSI Approved :: MIT License
Classifier: Operating System :: OS Independent
Requires-Python: >=3.7
License-File: LICENSE
Requires-Dist: pandas
Requires-Dist: numpy
Requires-Dist: pycountry
Requires-Dist: pycountry-convert
Requires-Dist: pyvis
Requires-Dist: seaborn
Requires-Dist: matplotlib
Requires-Dist: collections
Dynamic: author
Dynamic: author-email
Dynamic: classifier
Dynamic: description
Dynamic: description-content-type
Dynamic: home-page
Dynamic: license-file
Dynamic: requires-dist
Dynamic: requires-python
Dynamic: summary
